[
    {
        "id": 0,
        "seek": 0,
        "start": 0.0,
        "end": 1.52,
        "text": " Come and sit on a rock.",
        "tokens": [
            50363,
            7911,
            290,
            1650,
            319,
            257,
            3881,
            13,
            50439
        ],
        "temperature": 0.0,
        "avg_logprob": -0.34572365704704733,
        "compression_ratio": 1.356164383561644,
        "no_speech_prob": 0.01958448439836502
    },
    {
        "id": 1,
        "seek": 0,
        "start": 1.52,
        "end": 5.08,
        "text": " Overlooking the river's blow, he wears a hat and some glasses.",
        "tokens": [
            50439,
            3827,
            11534,
            262,
            7850,
            338,
            6611,
            11,
            339,
            17326,
            257,
            6877,
            290,
            617,
            15232,
            13,
            50617
        ],
        "temperature": 0.0,
        "avg_logprob": -0.34572365704704733,
        "compression_ratio": 1.356164383561644,
        "no_speech_prob": 0.01958448439836502
    },
    {
        "id": 2,
        "seek": 0,
        "start": 5.08,
        "end": 7.36,
        "text": " A smile on his face.",
        "tokens": [
            50617,
            317,
            8212,
            319,
            465,
            1986,
            13,
            50731
        ],
        "temperature": 0.0,
        "avg_logprob": -0.34572365704704733,
        "compression_ratio": 1.356164383561644,
        "no_speech_prob": 0.01958448439836502
    },
    {
        "id": 3,
        "seek": 0,
        "start": 7.36,
        "end": 8.56,
        "text": " He's not lost.",
        "tokens": [
            50731,
            679,
            338,
            407,
            2626,
            13,
            50791
        ],
        "temperature": 0.0,
        "avg_logprob": -0.34572365704704733,
        "compression_ratio": 1.356164383561644,
        "no_speech_prob": 0.01958448439836502
    },
    {
        "id": 4,
        "seek": 0,
        "start": 8.56,
        "end": 10.4,
        "text": " The water rushes by.",
        "tokens": [
            50791,
            383,
            1660,
            38596,
            416,
            13,
            50883
        ],
        "temperature": 0.0,
        "avg_logprob": -0.34572365704704733,
        "compression_ratio": 1.356164383561644,
        "no_speech_prob": 0.01958448439836502
    },
    {
        "id": 5,
        "seek": 0,
        "start": 10.4,
        "end": 12.08,
        "text": " A constant sound.",
        "tokens": [
            50883,
            317,
            6937,
            2128,
            13,
            50967
        ],
        "temperature": 0.0,
        "avg_logprob": -0.34572365704704733,
        "compression_ratio": 1.356164383561644,
        "no_speech_prob": 0.01958448439836502
    },
    {
        "id": 6,
        "seek": 0,
        "start": 12.08,
        "end": 13.68,
        "text": " It takes in the view.",
        "tokens": [
            50967,
            632,
            2753,
            287,
            262,
            1570,
            13,
            51047
        ],
        "temperature": 0.0,
        "avg_logprob": -0.34572365704704733,
        "compression_ratio": 1.356164383561644,
        "no_speech_prob": 0.01958448439836502
    },
    {
        "id": 7,
        "seek": 0,
        "start": 13.68,
        "end": 14.48,
        "text": " The mountains.",
        "tokens": [
            51047,
            383,
            12269,
            13,
            51087
        ],
        "temperature": 0.0,
        "avg_logprob": -0.34572365704704733,
        "compression_ratio": 1.356164383561644,
        "no_speech_prob": 0.01958448439836502
    }
]